pyzmo/__init__.py
pyzmo/decorators.py
pyzmo/dsl.hy
pyzmo/handler.py
pyzmo/util.py
pyzmo-1.0.0.dist-info/DESCRIPTION.rst
pyzmo-1.0.0.dist-info/METADATA
pyzmo-1.0.0.dist-info/RECORD
pyzmo-1.0.0.dist-info/WHEEL
pyzmo-1.0.0.dist-info/metadata.json
pyzmo-1.0.0.dist-info/top_level.txt
pyzmo-1.0.0.dist-info/zip-safe
